cdk_factory/__init__.py
cdk_factory/app.py
cdk_factory/cdk.json
cdk_factory/cli.py
cdk_factory/version.py
cdk_factory/builds/README.md
cdk_factory/commands/command_loader.py
cdk_factory/configurations/base_config.py
cdk_factory/configurations/cdk_config.py
cdk_factory/configurations/deployment.py
cdk_factory/configurations/deployment_wave.py
cdk_factory/configurations/devops.py
cdk_factory/configurations/enhanced_base_config.py
cdk_factory/configurations/enhanced_ssm_config.py
cdk_factory/configurations/management.py
cdk_factory/configurations/pipeline.py
cdk_factory/configurations/pipeline_stage.py
cdk_factory/configurations/stack.py
cdk_factory/configurations/workload.py
cdk_factory/configurations/resources/_resources.py
cdk_factory/configurations/resources/acm.py
cdk_factory/configurations/resources/api_gateway.py
cdk_factory/configurations/resources/apigateway_route_config.py
cdk_factory/configurations/resources/auto_scaling.py
cdk_factory/configurations/resources/cloudfront.py
cdk_factory/configurations/resources/cloudwatch_widget.py
cdk_factory/configurations/resources/code_artifact.py
cdk_factory/configurations/resources/code_artifact_login.py
cdk_factory/configurations/resources/code_repository.py
cdk_factory/configurations/resources/cognito.py
cdk_factory/configurations/resources/docker.py
cdk_factory/configurations/resources/dynamodb.py
cdk_factory/configurations/resources/ecr.py
cdk_factory/configurations/resources/ecs_capacity_provider.py
cdk_factory/configurations/resources/ecs_cluster.py
cdk_factory/configurations/resources/ecs_service.py
cdk_factory/configurations/resources/exisiting.py
cdk_factory/configurations/resources/lambda_edge.py
cdk_factory/configurations/resources/lambda_function.py
cdk_factory/configurations/resources/lambda_layers.py
cdk_factory/configurations/resources/lambda_triggers.py
cdk_factory/configurations/resources/load_balancer.py
cdk_factory/configurations/resources/monitoring.py
cdk_factory-0.45.0.dist-info/METADATA
cdk_factory-0.45.0.dist-info/WHEEL
cdk_factory-0.45.0.dist-info/entry_points.txt
cdk_factory-0.45.0.dist-info/licenses/LICENSE
cdk_factory-0.45.0.dist-info/RECORD
