Metadata-Version: 2.4
Name: cdk_factory
Version: 0.45.0
Summary: CDK Factory. A QuickStarter and best practices setup for CDK projects
Author-email: Eric Wilson <eric.wilson@geekcafe.com>
License: MIT License
License-File: LICENSE
Classifier: License :: OSI Approved :: MIT License
Classifier: Operating System :: OS Independent
Classifier: Programming Language :: Python :: 3
Requires-Python: >=3.10
Requires-Dist: aws-cdk-lib==2.202.0
Requires-Dist: aws-lambda-powertools>=2.38.1
Requires-Dist: boto3-assist>=0.10.0
Requires-Dist: cdk-nag
Requires-Dist: constructs
Requires-Dist: pyyaml
